README.md
setup.py
cpp_extensions/open_registration_extension.cpp
pytorch_cfu.egg-info/PKG-INFO
pytorch_cfu.egg-info/SOURCES.txt
pytorch_cfu.egg-info/dependency_links.txt
pytorch_cfu.egg-info/top_level.txt
utils/__init__.py
utils/custom_device_mode.py