Metadata-Version: 2.1
Name: pytorch-cfu
Version: 0.0.2
Summary: A Simple Pytorch version for CFU
Home-page: https://github.com/ggangliu/pytorch-cfu
Author: ggangliu
Author-email: ggang.liu@gmail.com
